odoo/addons/hr_attendance_reason/README.rst
odoo/addons/hr_attendance_reason/__init__.py
odoo/addons/hr_attendance_reason/__manifest__.py
odoo/addons/hr_attendance_reason/demo/hr_attendance_reason_demo.xml
odoo/addons/hr_attendance_reason/i18n/bg.po
odoo/addons/hr_attendance_reason/i18n/es.po
odoo/addons/hr_attendance_reason/i18n/fr.po
odoo/addons/hr_attendance_reason/i18n/hr_attendance_reason.pot
odoo/addons/hr_attendance_reason/i18n/it.po
odoo/addons/hr_attendance_reason/models/__init__.py
odoo/addons/hr_attendance_reason/models/hr_attendance.py
odoo/addons/hr_attendance_reason/models/hr_attendance_reason.py
odoo/addons/hr_attendance_reason/models/hr_employee_base.py
odoo/addons/hr_attendance_reason/models/res_company.py
odoo/addons/hr_attendance_reason/models/res_config_settings.py
odoo/addons/hr_attendance_reason/readme/CONTRIBUTORS.rst
odoo/addons/hr_attendance_reason/readme/DESCRIPTION.rst
odoo/addons/hr_attendance_reason/readme/USAGE.rst
odoo/addons/hr_attendance_reason/security/ir.model.access.csv
odoo/addons/hr_attendance_reason/security/security.xml
odoo/addons/hr_attendance_reason/static/description/icon.png
odoo/addons/hr_attendance_reason/static/description/index.html
odoo/addons/hr_attendance_reason/static/src/js/kiosk_confirm.js
odoo/addons/hr_attendance_reason/static/src/js/my_attendances.js
odoo/addons/hr_attendance_reason/static/src/scss/hr_attendance_reason.scss
odoo/addons/hr_attendance_reason/static/src/xml/attendance.xml
odoo/addons/hr_attendance_reason/tests/__init__.py
odoo/addons/hr_attendance_reason/tests/test_hr_attendance_reason.py
odoo/addons/hr_attendance_reason/views/assets.xml
odoo/addons/hr_attendance_reason/views/hr_attendance_reason_view.xml
odoo/addons/hr_attendance_reason/views/hr_attendance_view.xml
odoo/addons/hr_attendance_reason/views/res_config_settings_view.xml
odoo14_addon_hr_attendance_reason-14.0.1.1.4.dist-info/METADATA
odoo14_addon_hr_attendance_reason-14.0.1.1.4.dist-info/WHEEL
odoo14_addon_hr_attendance_reason-14.0.1.1.4.dist-info/top_level.txt
odoo14_addon_hr_attendance_reason-14.0.1.1.4.dist-info/RECORD
